LICENSE
justnow/__init__.py
justnow/justnow.lark
justnow/parser.py
justnow-0.1.4.dist-info/LICENSE
justnow-0.1.4.dist-info/WHEEL
justnow-0.1.4.dist-info/METADATA
justnow-0.1.4.dist-info/RECORD
