Metadata-Version: 2.1
Name: justnow
Version: 0.1.4
Summary: A systemd.timer inspired event parser in pure Python.
Home-page: https://gitlab.com/BradleyKirton/justnow
License: MIT
Keywords: systemd.timer,datetime,scheduling
Author: Bradley Stuart Kirton
Author-email: bradleykirton@gmail.com
Requires-Python: >=3.8,<4.0
Classifier: License :: OSI Approved :: MIT License
Classifier: Operating System :: MacOS
Classifier: Operating System :: Microsoft :: Windows
Classifier: Operating System :: POSIX :: Linux
Classifier: Programming Language :: Python :: 3
Classifier: Programming Language :: Python :: 3.8
Classifier: Programming Language :: Python :: Implementation :: CPython
Classifier: Topic :: Software Development :: Libraries
Requires-Dist: lark-parser (>=0.9.0,<0.10.0)
Project-URL: Repository, https://gitlab.com/BradleyKirton/justnow
